Workbook

Sheet 1. Operaciones
B3: ID_Operación | C3: Fecha | D3: Cliente | E3: Código Producto | F3: País Destino | G3: Unidades | H3: Precio FOB | I3: Costo Unitario | J3: Estado | K3: Producto | L3: Categoría | M3: Región | N3: Arancel % | O3: Clasificación Mercado | P3: Valor FOB | Q3: Costo Total | R3: Utilidad | S3: Margen | T3: Nivel de Rentabilidad | U3: Nivel de Operación (Valor FOB) | V3: Prioridad Comercial
B4: EX001 | C4: 46027 | D4: Comercial Maya | E4: P003 | F4: Guatemala | G4: 850 | H4: 4.8 | I4: 3.2 | J4: Embarcado | K4: =VLOOKUP(E4,'2. Productos'!$C$4:$F$8,2,FALSE()) -> Miel natural | L4: =VLOOKUP(E4,'2. Productos'!$C$4:$F$8,3,FALSE()) -> Apícola | M4: =VLOOKUP(F4,'3. Mercados'!$C$4:$F$9,2,FALSE()) -> Centroamérica | N4: =VLOOKUP(F4,'3. Mercados'!$C$4:$F$9,3,FALSE()) -> 0.03 | O4: =VLOOKUP(F4,'3. Mercados'!$C$4:$F$9,4,FALSE()) -> Estratégico | P4: =G4*H4 -> 4080 | Q4: =G4*I4 -> 2720 | R4: =P4-Q4 -> 1360 | S4: =R4/P4 -> 0.33333333 | T4: =IF(S4>=0.3,"Alta",IF(S4>=0.15,"Media","Baja")) -> Alta | U4: =IF(P4>=10000,"Grande",IF(P4>=5000,"Mediana","Pequeña")) -> Pequeña | V4: =IF(AND(O4="Estratégico",S4>=0.3),"Alta",IF(AND(O4="Estratégico",S4<0.3),"Media",IF(AND(O4="Potencial",S4>=0.3),"Media","Baja"))) -> Alta
B5: EX002 | C5: 46034 | D5: Global Foods | E5: P001 | F5: EE.UU. | G5: 1200 | H5: 6.5 | I5: 4.1 | J5: Entregado | K5: =VLOOKUP(E5,'2. Productos'!$C$4:$F$8,2,FALSE()) -> Café especial | L5: =VLOOKUP(E5,'2. Productos'!$C$4:$F$8,3,FALSE()) -> Café | M5: =VLOOKUP(F5,'3. Mercados'!$C$4:$F$9,2,FALSE()) -> Norteamérica | N5: =VLOOKUP(F5,'3. Mercados'!$C$4:$F$9,3,FALSE()) -> 0.05 | O5: =VLOOKUP(F5,'3. Mercados'!$C$4:$F$9,4,FALSE()) -> Estratégico | P5: =G5*H5 -> 7800 | Q5: =G5*I5 -> 4920 | R5: =P5-Q5 -> 2880 | S5: =R5/P5 -> 0.36923077 | T5: =IF(S5>=0.3,"Alta",IF(S5>=0.15,"Media","Baja")) -> Alta | U5: =IF(P5>=10000,"Grande",IF(P5>=5000,"Mediana","Pequeña")) -> Mediana | V5: =IF(AND(O5="Estratégico",S5>=0.3),"Alta",IF(AND(O5="Estratégico",S5<0.3),"Media",IF(AND(O5="Potencial",S5>=0.3),"Media","Baja"))) -> Alta
B6: EX003 | C6: 46042 | D6: Distribuidora Tica | E6: P004 | F6: Costa Rica | G6: 650 | H6: 8.2 | I6: 5.9 | J6: Embarcado | K6: =VLOOKUP(E6,'2. Productos'!$C$4:$F$8,2,FALSE()) -> Maní procesado | L6: =VLOOKUP(E6,'2. Productos'!$C$4:$F$8,3,FALSE()) -> Semillas | M6: =VLOOKUP(F6,'3. Mercados'!$C$4:$F$9,2,FALSE()) -> Centroamérica | N6: =VLOOKUP(F6,'3. Mercados'!$C$4:$F$9,3,FALSE()) -> 0.02 | O6: =VLOOKUP(F6,'3. Mercados'!$C$4:$F$9,4,FALSE()) -> Estratégico | P6: =G6*H6 -> 5330 | Q6: =G6*I6 -> 3835 | R6: =P6-Q6 -> 1495 | S6: =R6/P6 -> 0.2804878 | T6: =IF(S6>=0.3,"Alta",IF(S6>=0.15,"Media","Baja")) -> Media | U6: =IF(P6>=10000,"Grande",IF(P6>=5000,"Mediana","Pequeña")) -> Mediana | V6: =IF(AND(O6="Estratégico",S6>=0.3),"Alta",IF(AND(O6="Estratégico",S6<0.3),"Media",IF(AND(O6="Potencial",S6>=0.3),"Media","Baja"))) -> Media
B7: EX004 | C7: 46056 | D7: Iberia Foods | E7: P002 | F7: España | G7: 950 | H7: 7.1 | I7: 4.8 | J7: Pendiente | K7: =VLOOKUP(E7,'2. Productos'!$C$4:$F$8,2,FALSE()) -> Cacao en grano | L7: =VLOOKUP(E7,'2. Productos'!$C$4:$F$8,3,FALSE()) -> Cacao | M7: =VLOOKUP(F7,'3. Mercados'!$C$4:$F$9,2,FALSE()) -> Europa | N7: =VLOOKUP(F7,'3. Mercados'!$C$4:$F$9,3,FALSE()) -> 0.1 | O7: =VLOOKUP(F7,'3. Mercados'!$C$4:$F$9,4,FALSE()) -> Potencial | P7: =G7*H7 -> 6745 | Q7: =G7*I7 -> 4560 | R7: =P7-Q7 -> 2185 | S7: =R7/P7 -> 0.32394366 | T7: =IF(S7>=0.3,"Alta",IF(S7>=0.15,"Media","Baja")) -> Alta | U7: =IF(P7>=10000,"Grande",IF(P7>=5000,"Mediana","Pequeña")) -> Mediana | V7: =IF(AND(O7="Estratégico",S7>=0.3),"Alta",IF(AND(O7="Estratégico",S7<0.3),"Media",IF(AND(O7="Potencial",S7>=0.3),"Media","Baja"))) -> Media
B8: EX005 | C8: 46068 | D8: Comercial Azteca | E8: P005 | F8: México | G8: 500 | H8: 12.5 | I8: 8.7 | J8: Entregado | K8: =VLOOKUP(E8,'2. Productos'!$C$4:$F$8,2,FALSE()) -> Aceite de ajonjolí | L8: =VLOOKUP(E8,'2. Productos'!$C$4:$F$8,3,FALSE()) -> Aceites | M8: =VLOOKUP(F8,'3. Mercados'!$C$4:$F$9,2,FALSE()) -> Norteamérica | N8: =VLOOKUP(F8,'3. Mercados'!$C$4:$F$9,3,FALSE()) -> 0.08 | O8: =VLOOKUP(F8,'3. Mercados'!$C$4:$F$9,4,FALSE()) -> Potencial | P8: =G8*H8 -> 6250 | Q8: =G8*I8 -> 4350 | R8: =P8-Q8 -> 1900 | S8: =R8/P8 -> 0.304 | T8: =IF(S8>=0.3,"Alta",IF(S8>=0.15,"Media","Baja")) -> Alta | U8: =IF(P8>=10000,"Grande",IF(P8>=5000,"Mediana","Pequeña")) -> Mediana | V8: =IF(AND(O8="Estratégico",S8>=0.3),"Alta",IF(AND(O8="Estratégico",S8<0.3),"Media",IF(AND(O8="Potencial",S8>=0.3),"Media","Baja"))) -> Media
B9: EX006 | C9: 46081 | D9: Global Foods | E9: P003 | F9: EE.UU. | G9: 1400 | H9: 4.8 | I9: 3.2 | J9: Entregado | K9: =VLOOKUP(E9,'2. Productos'!$C$4:$F$8,2,FALSE()) -> Miel natural | L9: =VLOOKUP(E9,'2. Productos'!$C$4:$F$8,3,FALSE()) -> Apícola | M9: =VLOOKUP(F9,'3. Mercados'!$C$4:$F$9,2,FALSE()) -> Norteamérica | N9: =VLOOKUP(F9,'3. Mercados'!$C$4:$F$9,3,FALSE()) -> 0.05 | O9: =VLOOKUP(F9,'3. Mercados'!$C$4:$F$9,4,FALSE()) -> Estratégico | P9: =G9*H9 -> 6720 | Q9: =G9*I9 -> 4480 | R9: =P9-Q9 -> 2240 | S9: =R9/P9 -> 0.33333333 | T9: =IF(S9>=0.3,"Alta",IF(S9>=0.15,"Media","Baja")) -> Alta | U9: =IF(P9>=10000,"Grande",IF(P9>=5000,"Mediana","Pequeña")) -> Mediana | V9: =IF(AND(O9="Estratégico",S9>=0.3),"Alta",IF(AND(O9="Estratégico",S9<0.3),"Media",IF(AND(O9="Potencial",S9>=0.3),"Media","Baja"))) -> Alta
B10: EX007 | C10: 46089 | D10: Distribuidora Tica | E10: P001 | F10: Costa Rica | G10: 900 | H10: 6.5 | I10: 4.1 | J10: Embarcado | K10: =VLOOKUP(E10,'2. Productos'!$C$4:$F$8,2,FALSE()) -> Café especial | L10: =VLOOKUP(E10,'2. Productos'!$C$4:$F$8,3,FALSE()) -> Café | M10: =VLOOKUP(F10,'3. Mercados'!$C$4:$F$9,2,FALSE()) -> Centroamérica | N10: =VLOOKUP(F10,'3. Mercados'!$C$4:$F$9,3,FALSE()) -> 0.02 | O10: =VLOOKUP(F10,'3. Mercados'!$C$4:$F$9,4,FALSE()) -> Estratégico | P10: =G10*H10 -> 5850 | Q10: =G10*I10 -> 3690 | R10: =P10-Q10 -> 2160 | S10: =R10/P10 -> 0.36923077 | T10: =IF(S10>=0.3,"Alta",IF(S10>=0.15,"Media","Baja")) -> Alta | U10: =IF(P10>=10000,"Grande",IF(P10>=5000,"Mediana","Pequeña")) -> Mediana | V10: =IF(AND(O10="Estratégico",S10>=0.3),"Alta",IF(AND(O10="Estratégico",S10<0.3),"Media",IF(AND(O10="Potencial",S10>=0.3),"Media","Baja"))) -> Alta
B11: EX008 | C11: 46099 | D11: Comercial Maya | E11: P004 | F11: Guatemala | G11: 750 | H11: 8.2 | I11: 5.9 | J11: Entregado | K11: =VLOOKUP(E11,'2. Productos'!$C$4:$F$8,2,FALSE()) -> Maní procesado | L11: =VLOOKUP(E11,'2. Productos'!$C$4:$F$8,3,FALSE()) -> Semillas | M11: =VLOOKUP(F11,'3. Mercados'!$C$4:$F$9,2,FALSE()) -> Centroamérica | N11: =VLOOKUP(F11,'3. Mercados'!$C$4:$F$9,3,FALSE()) -> 0.03 | O11: =VLOOKUP(F11,'3. Mercados'!$C$4:$F$9,4,FALSE()) -> Estratégico | P11: =G11*H11 -> 6150 | Q11: =G11*I11 -> 4425 | R11: =P11-Q11 -> 1725 | S11: =R11/P11 -> 0.2804878 | T11: =IF(S11>=0.3,"Alta",IF(S11>=0.15,"Media","Baja")) -> Media | U11: =IF(P11>=10000,"Grande",IF(P11>=5000,"Mediana","Pequeña")) -> Mediana | V11: =IF(AND(O11="Estratégico",S11>=0.3),"Alta",IF(AND(O11="Estratégico",S11<0.3),"Media",IF(AND(O11="Potencial",S11>=0.3),"Media","Baja"))) -> Media
B12: EX009 | C12: 46106 | D12: Iberia Foods | E12: P005 | F12: España | G12: 600 | H12: 12.5 | I12: 8.7 | J12: Embarcado | K12: =VLOOKUP(E12,'2. Productos'!$C$4:$F$8,2,FALSE()) -> Aceite de ajonjolí | L12: =VLOOKUP(E12,'2. Productos'!$C$4:$F$8,3,FALSE()) -> Aceites | M12: =VLOOKUP(F12,'3. Mercados'!$C$4:$F$9,2,FALSE()) -> Europa | N12: =VLOOKUP(F12,'3. Mercados'!$C$4:$F$9,3,FALSE()) -> 0.1 | O12: =VLOOKUP(F12,'3. Mercados'!$C$4:$F$9,4,FALSE()) -> Potencial | P12: =G12*H12 -> 7500 | Q12: =G12*I12 -> 5220 | R12: =P12-Q12 -> 2280 | S12: =R12/P12 -> 0.304 | T12: =IF(S12>=0.3,"Alta",IF(S12>=0.15,"Media","Baja")) -> Alta | U12: =IF(P12>=10000,"Grande",IF(P12>=5000,"Mediana","Pequeña")) -> Mediana | V12: =IF(AND(O12="Estratégico",S12>=0.3),"Alta",IF(AND(O12="Estratégico",S12<0.3),"Media",IF(AND(O12="Potencial",S12>=0.3),"Media","Baja"))) -> Media
B13: EX010 | C13: 46114 | D13: Comercial Azteca | E13: P002 | F13: México | G13: 1100 | H13: 7.1 | I13: 4.8 | J13: Entregado | K13: =VLOOKUP(E13,'2. Productos'!$C$4:$F$8,2,FALSE()) -> Cacao en grano | L13: =VLOOKUP(E13,'2. Productos'!$C$4:$F$8,3,FALSE()) -> Cacao | M13: =VLOOKUP(F13,'3. Mercados'!$C$4:$F$9,2,FALSE()) -> Norteamérica | N13: =VLOOKUP(F13,'3. Mercados'!$C$4:$F$9,3,FALSE()) -> 0.08 | O13: =VLOOKUP(F13,'3. Mercados'!$C$4:$F$9,4,FALSE()) -> Potencial | P13: =G13*H13 -> 7810 | Q13: =G13*I13 -> 5280 | R13: =P13-Q13 -> 2530 | S13: =R13/P13 -> 0.32394366 | T13: =IF(S13>=0.3,"Alta",IF(S13>=0.15,"Media","Baja")) -> Alta | U13: =IF(P13>=10000,"Grande",IF(P13>=5000,"Mediana","Pequeña")) -> Mediana | V13: =IF(AND(O13="Estratégico",S13>=0.3),"Alta",IF(AND(O13="Estratégico",S13<0.3),"Media",IF(AND(O13="Potencial",S13>=0.3),"Media","Baja"))) -> Media
B14: EX011 | C14: 46122 | D14: Global Foods | E14: P004 | F14: EE.UU. | G14: 1300 | H14: 8.2 | I14: 5.9 | J14: Entregado | K14: =VLOOKUP(E14,'2. Productos'!$C$4:$F$8,2,FALSE()) -> Maní procesado | L14: =VLOOKUP(E14,'2. Productos'!$C$4:$F$8,3,FALSE()) -> Semillas | M14: =VLOOKUP(F14,'3. Mercados'!$C$4:$F$9,2,FALSE()) -> Norteamérica | N14: =VLOOKUP(F14,'3. Mercados'!$C$4:$F$9,3,FALSE()) -> 0.05 | O14: =VLOOKUP(F14,'3. Mercados'!$C$4:$F$9,4,FALSE()) -> Estratégico | P14: =G14*H14 -> 10660 | Q14: =G14*I14 -> 7670 | R14: =P14-Q14 -> 2990 | S14: =R14/P14 -> 0.2804878 | T14: =IF(S14>=0.3,"Alta",IF(S14>=0.15,"Media","Baja")) -> Media | U14: =IF(P14>=10000,"Grande",IF(P14>=5000,"Mediana","Pequeña")) -> Grande | V14: =IF(AND(O14="Estratégico",S14>=0.3),"Alta",IF(AND(O14="Estratégico",S14<0.3),"Media",IF(AND(O14="Potencial",S14>=0.3),"Media","Baja"))) -> Media
B15: EX012 | C15: 46130 | D15: Comercial Maya | E15: P001 | F15: Guatemala | G15: 700 | H15: 6.5 | I15: 4.1 | J15: Pendiente | K15: =VLOOKUP(E15,'2. Productos'!$C$4:$F$8,2,FALSE()) -> Café especial | L15: =VLOOKUP(E15,'2. Productos'!$C$4:$F$8,3,FALSE()) -> Café | M15: =VLOOKUP(F15,'3. Mercados'!$C$4:$F$9,2,FALSE()) -> Centroamérica | N15: =VLOOKUP(F15,'3. Mercados'!$C$4:$F$9,3,FALSE()) -> 0.03 | O15: =VLOOKUP(F15,'3. Mercados'!$C$4:$F$9,4,FALSE()) -> Estratégico | P15: =G15*H15 -> 4550 | Q15: =G15*I15 -> 2870 | R15: =P15-Q15 -> 1680 | S15: =R15/P15 -> 0.36923077 | T15: =IF(S15>=0.3,"Alta",IF(S15>=0.15,"Media","Baja")) -> Alta | U15: =IF(P15>=10000,"Grande",IF(P15>=5000,"Mediana","Pequeña")) -> Pequeña | V15: =IF(AND(O15="Estratégico",S15>=0.3),"Alta",IF(AND(O15="Estratégico",S15<0.3),"Media",IF(AND(O15="Potencial",S15>=0.3),"Media","Baja"))) -> Alta
... B103: EX100 | C103: 46150 | D103: Comercial Azteca | E103: P001 | F103: México | G103: 1170 | H103: 6.5 | I103: 4.1 | J103: Entregado | K103: =VLOOKUP(E103,'2. Productos'!$C$4:$F$8,2,FALSE()) -> Café especial | L103: =VLOOKUP(E103,'2. Productos'!$C$4:$F$8,3,FALSE()) -> Café | M103: =VLOOKUP(F103,'3. Mercados'!$C$4:$F$9,2,FALSE()) -> Norteamérica | N103: =VLOOKUP(F103,'3. Mercados'!$C$4:$F$9,3,FALSE()) -> 0.08 | O103: =VLOOKUP(F103,'3. Mercados'!$C$4:$F$9,4,FALSE()) -> Potencial | P103: =G103*H103 -> 7605 | Q103: =G103*I103 -> 4797 | R103: =P103-Q103 -> 2808 | S103: =R103/P103 -> 0.36923077 | T103: =IF(S103>=0.3,"Alta",IF(S103>=0.15,"Media","Baja")) -> Alta | U103: =IF(P103>=10000,"Grande",IF(P103>=5000,"Mediana","Pequeña")) -> Mediana | V103: =IF(AND(O103="Estratégico",S103>=0.3),"Alta",IF(AND(O103="Estratégico",S103<0.3),"Media",IF(AND(O103="Potencial",S103>=0.3),"Media","Baja"))) -> Media

Sheet 2. Productos
C2: Catálogo de Productos
C3: Código | D3: Producto | E3: Categoría | F3: Unidad de Medida
C4: P001 | D4: Café especial | E4: Café | F4: Kg
C5: P002 | D5: Cacao en grano | E5: Cacao | F5: Kg
C6: P003 | D6: Miel natural | E6: Apícola | F6: Kg
C7: P004 | D7: Maní procesado | E7: Semillas | F7: Kg
C8: P005 | D8: Aceite de ajonjolí | E8: Aceites | F8: Litro

Sheet 3. Mercados
C2: Mercados
C3: País | D3: Región | E3: Arancel % | F3: Clasificación
C4: EE.UU. | D4: Norteamérica | E4: 0.05 | F4: Estratégico
C5: México | D5: Norteamérica | E5: 0.08 | F5: Potencial
C6: Guatemala | D6: Centroamérica | E6: 0.03 | F6: Estratégico
C7: Costa Rica | D7: Centroamérica | E7: 0.02 | F7: Estratégico
C8: El Salvador | D8: Centroamérica | E8: 0.02 | F8: Potencial
C9: España | D9: Europa | E9: 0.1 | F9: Potencial

Sheet 4. Preguntas
B2: Respuestas a las Preguntas de Análisis (Punto 9 de la Guía)
B3: Nº | C3: Pregunta | D3: Fórmula (Excel, notación en español) | E3: Resultado | G3: Región (aux) | H3: Margen Promedio (aux)
B4: 1 | C4: ¿Cuántas operaciones internacionales se realizaron? | D4: contara(B4:B103) | E4: =COUNTA('1. Operaciones'!$B$4:$B$103) -> 100 | G4: Norteamérica | H4: =AVERAGEIF('1. Operaciones'!$M$4:$M$103,G4,'1. Operaciones'!$S$4:$S$103) -> 0.32998701
B5: 2 | C5: ¿Cuántas operaciones están pendientes? | D5: contar.si(J4:J103,"Pendiente") | E5: =COUNTIF('1. Operaciones'!$J$4:$J$103,"Pendiente") -> 15 | G5: Centroamérica | H5: =AVERAGEIF('1. Operaciones'!$M$4:$M$103,G5,'1. Operaciones'!$S$4:$S$103) -> 0.32321297
B6: 3 | C6: ¿Cuál es el país con mayor cantidad de operaciones? | D6: indice(mercados!país,coincidir(MAX(contar.si(F:F,mercados!país)),contar.si(F:F,mercados!país),0)) | E6: =INDEX('5. Tablas Dinamicas'!$B$6:$B$11,MATCH(MAX('5. Tablas Dinamicas'!$D$6:$D$11),'5. Tablas Dinamicas'!$D$6:$D$11,0)) -> EE.UU. | G6: Europa | H6: =AVERAGEIF('1. Operaciones'!$M$4:$M$103,G6,'1. Operaciones'!$S$4:$S$103) -> 0.32040424
B7: 4 | C7: ¿Cuál es el país que genera mayor valor FOB? | D7: indice(mercados!país,coincidir(MAX(sumar.si(F:F,mercados!país,P:P)),sumar.si(...),0)) | E7: =INDEX('5. Tablas Dinamicas'!$B$6:$B$11,MATCH(MAX('5. Tablas Dinamicas'!$C$6:$C$11),'5. Tablas Dinamicas'!$C$6:$C$11,0)) -> EE.UU.
B8: 5 | C8: ¿Cuál es el producto más exportado por unidades? | D8: indice(productos!producto,coincidir(MAX(sumar.si(K:K,productos!producto,G:G)),...,0)) | E8: =INDEX('5. Tablas Dinamicas'!$F$6:$F$10,MATCH(MAX('5. Tablas Dinamicas'!$G$6:$G$10),'5. Tablas Dinamicas'!$G$6:$G$10,0)) -> Café especial
B9: 6 | C9: ¿Cuál es el producto que genera mayor utilidad? | D9: indice(productos!producto,coincidir(MAX(sumar.si(K:K,productos!producto,R:R)),...,0)) | E9: =INDEX('5. Tablas Dinamicas'!$B$16:$B$20,MATCH(MAX('5. Tablas Dinamicas'!$C$16:$C$20),'5. Tablas Dinamicas'!$C$16:$C$20,0)) -> Café especial
B10: 7 | C10: ¿Cuál es el mercado (región) con mayor margen promedio? | D10: indice(mercados!región,coincidir(MAX(promedio.si(M:M,mercados!región,S:S)),...,0)) | E10: =INDEX(G4:G6,MATCH(MAX(H4:H6),H4:H6,0)) -> Norteamérica
B11: 8 | C11: ¿Cuántas operaciones tienen rentabilidad alta? | D11: contar.si(T4:T103,"Alta") | E11: =COUNTIF('1. Operaciones'!$T$4:$T$103,"Alta") -> 82
B12: 9 | C12: ¿Cuánto se exportó (Valor FOB) hacia Centroamérica? | D12: sumar.si(M4:M103,"Centroamérica",P4:P103) | E12: =SUMIF('1. Operaciones'!$M$4:$M$103,"Centroamérica",'1. Operaciones'!$P$4:$P$103) -> 232879
B13: 10 | C13: ¿Cuánto se exportó (Valor FOB) hacia Norteamérica? | D13: sumar.si(M4:M103,"Norteamérica",P4:P103) | E13: =SUMIF('1. Operaciones'!$M$4:$M$103,"Norteamérica",'1. Operaciones'!$P$4:$P$103) -> 289058
B14: 11 | C14: ¿Cuánto se exportó (Valor FOB) hacia Europa? | D14: sumar.si(M4:M103,"Europa",P4:P103) | E14: =SUMIF('1. Operaciones'!$M$4:$M$103,"Europa",'1. Operaciones'!$P$4:$P$103) -> 136328
B15: 12 | C15: ¿Cuántas operaciones tienen prioridad comercial alta? | D15: contar.si(V4:V103,"Alta") | E15: =COUNTIF('1. Operaciones'!$V$4:$V$103,"Alta") -> 48
B16: 13 | C16: ¿Qué cliente genera mayor valor de exportación? | D16: indice(D4:D103,coincidir(MAX(sumar.si(D:D,D:D,P:P)),sumar.si(D:D,D:D,P:P),0)) | E16: =INDEX('5. Tablas Dinamicas'!$F$15:$F$19,MATCH(MAX('5. Tablas Dinamicas'!$G$15:$G$19),'5. Tablas Dinamicas'!$G$15:$G$19,0)) -> Global Foods
B17: 14 | C17: ¿Cuántas operaciones requieren atención por estar pendientes? | D17: contar.si(J4:J103,"Pendiente") | E17: =COUNTIF('1. Operaciones'!$J$4:$J$103,"Pendiente") -> 15

Sheet 5. Tablas Dinamicas
B2: Tablas Resumen (equivalentes a Tablas Dinámicas)
B4: Tabla Dinámica 1: Valor FOB por País | F4: Tabla Auxiliar A: Unidades Exportadas por Producto
B5: País | C5: Valor FOB (Suma) | D5: Nº Operaciones | F5: Producto | G5: Unidades (Suma)
B6: EE.UU. | C6: =SUMIF('1. Operaciones'!$F$4:$F$103,B6,'1. Operaciones'!$P$4:$P$103) -> 168745 | D6: =COUNTIF('1. Operaciones'!$F$4:$F$103,B6) -> 20 | F6: Café especial | G6: =SUMIF('1. Operaciones'!$K$4:$K$103,F6,'1. Operaciones'!$G$4:$G$103) -> 26180
B7: México | C7: =SUMIF('1. Operaciones'!$F$4:$F$103,B7,'1. Operaciones'!$P$4:$P$103) -> 120313 | D7: =COUNTIF('1. Operaciones'!$F$4:$F$103,B7) -> 20 | F7: Cacao en grano | G7: =SUMIF('1. Operaciones'!$K$4:$K$103,F7,'1. Operaciones'!$G$4:$G$103) -> 16000
B8: Guatemala | C8: =SUMIF('1. Operaciones'!$F$4:$F$103,B8,'1. Operaciones'!$P$4:$P$103) -> 119335 | D8: =COUNTIF('1. Operaciones'!$F$4:$F$103,B8) -> 20 | F8: Miel natural | G8: =SUMIF('1. Operaciones'!$K$4:$K$103,F8,'1. Operaciones'!$G$4:$G$103) -> 24180
B9: Costa Rica | C9: =SUMIF('1. Operaciones'!$F$4:$F$103,B9,'1. Operaciones'!$P$4:$P$103) -> 113544 | D9: =COUNTIF('1. Operaciones'!$F$4:$F$103,B9) -> 20 | F9: Maní procesado | G9: =SUMIF('1. Operaciones'!$K$4:$K$103,F9,'1. Operaciones'!$G$4:$G$103) -> 14580
B10: El Salvador | C10: =SUMIF('1. Operaciones'!$F$4:$F$103,B10,'1. Operaciones'!$P$4:$P$103) -> 0 | D10: =COUNTIF('1. Operaciones'!$F$4:$F$103,B10) -> 0 | F10: Aceite de ajonjolí | G10: =SUMIF('1. Operaciones'!$K$4:$K$103,F10,'1. Operaciones'!$G$4:$G$103) -> 11110
B11: España | C11: =SUMIF('1. Operaciones'!$F$4:$F$103,B11,'1. Operaciones'!$P$4:$P$103) -> 136328 | D11: =COUNTIF('1. Operaciones'!$F$4:$F$103,B11) -> 20 | F11: Total | G11: =SUM(G6:G10) -> 92050
B12: Total | C12: =SUM(C6:C11) -> 658265 | D12: =SUM(D6:D11) -> 100
F13: Tabla Auxiliar B: Valor FOB por Cliente
B14: Tabla Dinámica 2: Utilidad por Producto | F14: Cliente | G14: Valor FOB (Suma)
B15: Producto | C15: Utilidad (Suma) | F15: Comercial Maya | G15: =SUMIF('1. Operaciones'!$D$4:$D$103,F15,'1. Operaciones'!$P$4:$P$103) -> 119335
B16: Café especial | C16: =SUMIF('1. Operaciones'!$K$4:$K$103,B16,'1. Operaciones'!$R$4:$R$103) -> 62832 | F16: Global Foods | G16: =SUMIF('1. Operaciones'!$D$4:$D$103,F16,'1. Operaciones'!$P$4:$P$103) -> 168745
B17: Cacao en grano | C17: =SUMIF('1. Operaciones'!$K$4:$K$103,B17,'1. Operaciones'!$R$4:$R$103) -> 36800 | F17: Distribuidora Tica | G17: =SUMIF('1. Operaciones'!$D$4:$D$103,F17,'1. Operaciones'!$P$4:$P$103) -> 113544
B18: Miel natural | C18: =SUMIF('1. Operaciones'!$K$4:$K$103,B18,'1. Operaciones'!$R$4:$R$103) -> 38688 | F18: Iberia Foods | G18: =SUMIF('1. Operaciones'!$D$4:$D$103,F18,'1. Operaciones'!$P$4:$P$103) -> 136328
B19: Maní procesado | C19: =SUMIF('1. Operaciones'!$K$4:$K$103,B19,'1. Operaciones'!$R$4:$R$103) -> 33534 | F19: Comercial Azteca | G19: =SUMIF('1. Operaciones'!$D$4:$D$103,F19,'1. Operaciones'!$P$4:$P$103) -> 120313
B20: Aceite de ajonjolí | C20: =SUMIF('1. Operaciones'!$K$4:$K$103,B20,'1. Operaciones'!$R$4:$R$103) -> 42218 | F20: Total | G20: =SUM(G15:G19) -> 658265
B21: Total | C21: =SUM(C16:C20) -> 214072
B23: Tabla Dinámica 3: Ventas (Valor FOB) por Región
B24: Región | C24: Valor FOB (Suma)
B25: Norteamérica | C25: =SUMIF('1. Operaciones'!$M$4:$M$103,B25,'1. Operaciones'!$P$4:$P$103) -> 289058
B26: Centroamérica | C26: =SUMIF('1. Operaciones'!$M$4:$M$103,B26,'1. Operaciones'!$P$4:$P$103) -> 232879
B27: Europa | C27: =SUMIF('1. Operaciones'!$M$4:$M$103,B27,'1. Operaciones'!$P$4:$P$103) -> 136328
B28: Total | C28: =SUM(C25:C27) -> 658265
B30: Tabla Dinámica 4: Operaciones por Clasificación de Prioridad
B31: Prioridad Comercial | C31: Nº Operaciones
B32: Alta | C32: =COUNTIF('1. Operaciones'!$V$4:$V$103,B32) -> 48
B33: Media | C33: =COUNTIF('1. Operaciones'!$V$4:$V$103,B33) -> 46
B34: Baja | C34: =COUNTIF('1. Operaciones'!$V$4:$V$103,B34) -> 6
B35: Total | C35: =SUM(C32:C34) -> 100

Sheet 6. Graficos
B2: Gráficos Analíticos
